spendwise_analytics_pkg/__init__.py
spendwise_analytics_pkg/analytics.py
smart_budgeting_pkg-0.1.0.dist-info/METADATA
smart_budgeting_pkg-0.1.0.dist-info/WHEEL
smart_budgeting_pkg-0.1.0.dist-info/top_level.txt
smart_budgeting_pkg-0.1.0.dist-info/RECORD
