Metadata-Version: 2.4
Name: smart-budgeting-pkg
Version: 0.1.0
Summary: Reusable budget projections & anomaly checks for Spendwise
Author: Manojkumar
License: MIT
Project-URL: Homepage, https://example.com/smart-budgeting-pkg
Project-URL: Changelog, https://example.com/smart-budgeting-pkg/changelog
Classifier: Programming Language :: Python :: 3
Classifier: License :: OSI Approved :: MIT License
Classifier: Intended Audience :: Developers
Classifier: Topic :: Office/Business :: Financial
Requires-Python: >=3.9
Dynamic: author
Dynamic: classifier
Dynamic: description
Dynamic: description-content-type
Dynamic: license
Dynamic: project-url
Dynamic: requires-python
Dynamic: summary
